numsys/__init__.py
numsys/complex_decimal.py
numsys/nonstandard.py
numsys/standard.py
numsys/support.py
numsys/tests.py
numsys-1.0.1.dist-info/LICENSE
numsys-1.0.1.dist-info/METADATA
numsys-1.0.1.dist-info/WHEEL
numsys-1.0.1.dist-info/top_level.txt
numsys-1.0.1.dist-info/RECORD
