Metadata-Version: 2.1
Name: numsys
Version: 1.0.1
Summary: numeral systems - number base conversion module
Home-page: http://github.com/Electrostatus/numsys
Author: Electrostatus
License: GPLv3
Keywords: number base numeral system mixed radix roman
Platform: UNKNOWN
Classifier: Operating System :: OS Independent
Classifier: License :: OSI Approved :: GNU General Public License v3 (GPLv3)
Classifier: Development Status :: 5 - Production/Stable
Classifier: Programming Language :: Python :: 2
Classifier: Programming Language :: Python :: 3
Classifier: Natural Language :: English
Classifier: Topic :: Scientific/Engineering :: Mathematics
Classifier: Intended Audience :: Education
License-File: LICENSE
